{
  "kind": "collectionType",
  "collectionName": "clubs",
  "info": {
    "singularName": "club",
    "pluralName": "clubs",
    "displayName": "club",
    "description": ""
  },
  "options": {
    "draftAndPublish": true
  },
  "pluginOptions": {},
  "attributes": {
    "name": {
      "type": "string"
    },
    "acronym": {
      "type": "string"
    },
    "websiteKey": {
      "type": "string",
      "unique": true
    },
    "uid": {
      "type": "uid"
    },
    "enable": {
      "type": "boolean"
    },
    "bgColor": {
      "type": "string"
    },
    "accentColor": {
      "type": "string"
    },
    "password": {
      "type": "password"
    },
    "manager": {
      "type": "relation",
      "relation": "oneToOne",
      "target": "plugin::users-permissions.user"
    }
  }
}
